TASK/4/LSP_BOILER_FSM/LSP_BOILER_FSM/BoilerFSM.vhd
library ieee; use ieee.std_logic_1164.all;use ieee.numeric_std.all;
entity BoilerFSM is
    port( CLK, RESET: in std_logic;
 start, full, boiling, Chef : in std_logic;
 water, fire, bell : out std_logic);
end;
architecture rtl of BoilerFSM is
begin
 iboiler : process (CLK) 
   type state_t is (S0, S1, S2, S3);
   variable state : state_t:=S0;
   begin
iRedge :if rising_edge(clk) then
  iDelta: if RESET then  state := S0; else
     iNext: case state is
              when S0 =>	if start  then  state := S1; end if;
              when S1 =>	if full  then state := S2; end if;
              when S2 =>	if boiling  then  state := S3; end if;
              when S3 =>	if Chef then state := S0; end if;
            end case iNext;
       end if iDelta; 
     end if iRedge;
     water <= '0'; fire<='0'; bell <= '0';
     case state is  
        when S0=>null;  
        when S1=> water <= '1';
        when S2=> fire<='1';  
        when S3=> bell <= '1';  
     end case;
  end process; 
end architecture;


architecture controlUnit of BoilerFSM is
signal debugPC : integer :=0;
begin
  iboiler : process (CLK) 
    type cmd_t is record  
      CondIx: integer range 0 to 3;  -- index of input
      WFB: std_logic_vector(0 to 2); -- Water, Fire, Bell values
   end record; 
   type mem_t is array(natural range <>) of cmd_t;
   constant MEM : mem_t := ((0,"000"),(1,"100"),(2,"010"),(3,"001"));
   variable pc : integer range 0 to MEM'HIGH:=0; --Program Counter
   variable Binputs : std_logic_vector(0 to 3):=(others=>'0');
   variable instr:cmd_t:=(0,"000");
   begin -- process
iRedge:if rising_edge(CLK) then
   iDelta:if RESET then pc:=0; instr:=(0,"000"); else
 instr:=MEM(pc);
 BInputs:=start & full & boiling & Chef; 
 if BInputs(instr.CondIx) then 
     if pc<MEM'HIGH then pc:=pc+1; else  pc:=0; end if;
 end if;
             end if iDelta;
          end if iRedge;
  water<=instr.WFB(0); fire<=instr.WFB(1);  bell<=instr.WFB(2);
  debugPC<=pc;  
 end process;  
end architecture;

architecture microCode of BoilerFSM is
signal dbgPCm : integer :=0;
begin
  iboiler : process (CLK) 
    type cmd_t is record  
      CondIx: integer range 0 to 3;  -- index of input
      brOpt: unsigned(1 downto 0);  -- condition "0-" no, "10":on ='0', "11":on ='1'
      brCondIx: integer range 0 to 3; --the index of a tested input
      brAddr: integer range 0 to 15;  --
      WFB: std_logic_vector(0 to 2); -- Water, Fire, Bell values
   end record; 
   type mem_t is array(natural range <>) of cmd_t;
   constant MEM : mem_t := ((0,"00",0,0,"000"),(1,"00",0,0,"100"),(2,"10",1,1,"010"),(3,"10",1,1,"001"));
   variable pc : integer range 0 to MEM'HIGH:=0; --Program Counter
   variable Binputs : std_logic_vector(0 to 3):=(others=>'0');
   constant INIT:cmd_t:=(0,"00",0,0,"000");
   variable instr:cmd_t:=INIT;
   begin -- process
iRedge:if rising_edge(CLK) then
   iDelta:if RESET then pc:=0; instr:=INIT; else
           instr:=MEM(pc);
           BInputs:=start & full & boiling & Chef; 
           if BInputs(instr.CondIx) then 
              if pc<MEM'HIGH then pc:=pc+1; else  pc:=0; end if;
           elsif instr.brOpt(1)='1' and BInputs(instr.brCondIx)=instr.brOpt(0) then
                if instr.brAddr<MEM'LENGTH then pc:=instr.brAddr; end if;
           end if;
         end if iDelta;
      end if iRedge;
  water<=instr.WFB(0); fire<=instr.WFB(1);  bell<=instr.WFB(2);
  dbgPCm<=pc;  
 end process;  
end architecture;

TASK/4_old/LSP_BOILER_FSM/LSP_BOILER_FSM/tb_BoilerMicroCode.vhd
library ieee; use ieee.std_logic_1164.all; use ieee.numeric_std.all;
library work;
entity tb_BoilerMicroCode is end entity;

architecture rtl OF tb_BoilerMicroCode is
signal reset,start,full,boiling,Chef:std_logic:='0';
signal water,fire,bell:std_logic:='0';
signal CLK:std_logic:='0';
 component BoilerFSM is
    port( CLK, RESET: in std_logic;
          start, full, boiling, Chef : in std_logic;
          water, fire, bell : out std_logic);
  end component;
type R_t is record D:std_logic_vector(0 to 4); T:TIME; 
end record;
type Stimul_t is array(natural range <>) of R_t;
-- compiler
function T2R(s:string;t:positive) return R_t is
variable result:R_t; 
variable v:std_logic_vector(result.D'RANGE);
begin v:="00000";
  iloop : for i in s'RANGE loop
             case s(i) is
               when 'R'=>v(0):='1';  when 'S'=>v(1):='1';
               when 'F'=>v(2):='1';  when 'B'=>v(3):='1';
               when 'C'=>v(4):='1';
               when others=> null;
            end case;
          end loop iloop;
          result.D:=v; result.T:=t*(1 sec); return result;
end function;
constant STIMULS:Stimul_t:=
(T2R("-",20),T2R("S",100),T2R("-",50), T2R("F",100),
 T2R("SF",40),T2R("-",40), T2R("F",50),T2R("FB",50),
 T2R("-",100), T2R("F",50),T2R("FB",50), T2R("FC",50),
 T2R("S",100),T2R("-",50), T2R("F",100), T2R("FR",50), 
 T2R("F",50), T2R("SF",50), T2R("FB",50),T2R("FC",50));

begin
   CLK <= not CLK after 1 sec;
    imc : entity work.BoilerFSM(microCode) 
       port map(CLK, RESET, start, full, boiling, Chef, water, fire, bell);
 
always : process -- onetime run only
    variable x:std_logic_vector(STIMULS(0).D'RANGE):=(others=>'0');
    begin
    irep: for j in 1 to 2 loop
     iloop:for ix in 0 to STIMULS'LENGTH-1 loop
             x:=STIMULS(ix).D;   
             RESET<=x(0); start<=x(1);full<=x(2);boiling <=x(3);Chef<=x(4);
            wait for j*STIMULS(ix).T;
      end loop iloop; 
    end loop irep;
    
    assert false report LF&":-) OK end"&LF severity failure;
    end process;
end architecture;

TASK/4/LSP_BOILER_FSM/LSP_BOILER_FSM/simulation/MySim.vcd
$date
  Tue Nov 25 16:36:47 2025
$end
$version
  GHDL v0
$end
$timescale
  1 fs
$end
$scope module standard $end
$upscope $end
$scope module textio $end
$upscope $end
$scope module std_logic_1164 $end
$upscope $end
$scope module numeric_std $end
$upscope $end
$scope module tb_boilermicrocode $end
$var reg 1 ! reset $end
$var reg 1 " start $end
$var reg 1 # full $end
$var reg 1 $ boiling $end
$var reg 1 % chef $end
$var reg 1 & water $end
$var reg 1 ' fire $end
$var reg 1 ( bell $end
$var reg 1 ) clk $end
$scope module imc $end
$var reg 1 * clk $end
$var reg 1 + reset $end
$var reg 1 , start $end
$var reg 1 - full $end
$var reg 1 . boiling $end
$var reg 1 / chef $end
$var reg 1 0 water $end
$var reg 1 1 fire $end
$var reg 1 2 bell $end
$var integer 32 3 dbgpcm $end
$upscope $end
$upscope $end
$enddefinitions $end
#0
0!
0"
0#
0$
0%
0&
0'
0(
0)
0*
0+
0,
0-
0.
0/
00
01
02
b0 3
#1000000000000000
1)
1*
#2000000000000000
0)
0*
#3000000000000000
1)
1*
#4000000000000000
0)
0*
#5000000000000000
1)
1*
#6000000000000000
0)
0*
#7000000000000000
1)
1*
#8000000000000000
0)
0*
#9000000000000000
1)
1*
#10000000000000000
0)
0*
#11000000000000000
1)
1*
#12000000000000000
0)
0*
#13000000000000000
1)
1*
#14000000000000000
0)
0*
#15000000000000000
1)
1*
#16000000000000000
0)
0*
#17000000000000000
1)
1*
#18000000000000000
0)
0*
#19000000000000000
1)
1*
#20000000000000000
1"
0)
0*
1,
#21000000000000000
1)
1*
b1 3
#22000000000000000
0)
0*
#23000000000000000
1&
1)
1*
10
#24000000000000000
0)
0*
#25000000000000000
1)
1*
#26000000000000000
0)
0*
#27000000000000000
1)
1*
#28000000000000000
0)
0*
#29000000000000000
1)
1*
#30000000000000000
0)
0*
#31000000000000000
1)
1*
#32000000000000000
0)
0*
#33000000000000000
1)
1*
#34000000000000000
0)
0*
#35000000000000000
1)
1*
#36000000000000000
0)
0*
#37000000000000000
1)
1*
#38000000000000000
0)
0*
#39000000000000000
1)
1*
#40000000000000000
0)
0*
#41000000000000000
1)
1*
#42000000000000000
0)
0*
#43000000000000000
1)
1*
#44000000000000000
0)
0*
#45000000000000000
1)
1*
#46000000000000000
0)
0*
#47000000000000000
1)
1*
#48000000000000000
0)
0*
#49000000000000000
1)
1*
#50000000000000000
0)
0*
#51000000000000000
1)
1*
#52000000000000000
0)
0*
#53000000000000000
1)
1*
#54000000000000000
0)
0*
#55000000000000000
1)
1*
#56000000000000000
0)
0*
#57000000000000000
1)
1*
#58000000000000000
0)
0*
#59000000000000000
1)
1*
#60000000000000000
0)
0*
#61000000000000000
1)
1*
#62000000000000000
0)
0*
#63000000000000000
1)
1*
#64000000000000000
0)
0*
#65000000000000000
1)
1*
#66000000000000000
0)
0*
#67000000000000000
1)
1*
#68000000000000000
0)
0*
#69000000000000000
1)
1*
#70000000000000000
0)
0*
#71000000000000000
1)
1*
#72000000000000000
0)
0*
#73000000000000000
1)
1*
#74000000000000000
0)
0*
#75000000000000000
1)
1*
#76000000000000000
0)
0*
#77000000000000000
1)
1*
#78000000000000000
0)
0*
#79000000000000000
1)
1*
#80000000000000000
0)
0*
#81000000000000000
1)
1*
#82000000000000000
0)
0*
#83000000000000000
1)
1*
#84000000000000000
0)
0*
#85000000000000000
1)
1*
#86000000000000000
0)
0*
#87000000000000000
1)
1*
#88000000000000000
0)
0*
#89000000000000000
1)
1*
#90000000000000000
0)
0*
#91000000000000000
1)
1*
#92000000000000000
0)
0*
#93000000000000000
1)
1*
#94000000000000000
0)
0*
#95000000000000000
1)
1*
#96000000000000000
0)
0*
#97000000000000000
1)
1*
#98000000000000000
0)
0*
#99000000000000000
1)
1*
#100000000000000000
0)
0*
#101000000000000000
1)
1*
#102000000000000000
0)
0*
#103000000000000000
1)
1*
#104000000000000000
0)
0*
#105000000000000000
1)
1*
#106000000000000000
0)
0*
#107000000000000000
1)
1*
#108000000000000000
0)
0*
#109000000000000000
1)
1*
#110000000000000000
0)
0*
#111000000000000000
1)
1*
#112000000000000000
0)
0*
#113000000000000000
1)
1*
#114000000000000000
0)
0*
#115000000000000000
1)
1*
#116000000000000000
0)
0*
#117000000000000000
1)
1*
#118000000000000000
0)
0*
#119000000000000000
1)
1*
#120000000000000000
0"
0)
0*
0,
#121000000000000000
1)
1*
#122000000000000000
0)
0*
#123000000000000000
1)
1*
#124000000000000000
0)
0*
#125000000000000000
1)
1*
#126000000000000000
0)
0*
#127000000000000000
1)
1*
#128000000000000000
0)
0*
#129000000000000000
1)
1*
#130000000000000000
0)
0*
#131000000000000000
1)
1*
#132000000000000000
0)
0*
#133000000000000000
1)
1*
#134000000000000000
0)
0*
#135000000000000000
1)
1*
#136000000000000000
0)
0*
#137000000000000000
1)
1*
#138000000000000000
0)
0*
#139000000000000000
1)
1*
#140000000000000000
0)
0*
#141000000000000000
1)
1*
#142000000000000000
0)
0*
#143000000000000000
1)
1*
#144000000000000000
0)
0*
#145000000000000000
1)
1*
#146000000000000000
0)
0*
#147000000000000000
1)
1*
#148000000000000000
0)
0*
#149000000000000000
1)
1*
#150000000000000000
0)
0*
#151000000000000000
1)
1*
#152000000000000000
0)
0*
#153000000000000000
1)
1*
#154000000000000000
0)
0*
#155000000000000000
1)
1*
#156000000000000000
0)
0*
#157000000000000000
1)
1*
#158000000000000000
0)
0*
#159000000000000000
1)
1*
#160000000000000000
0)
0*
#161000000000000000
1)
1*
#162000000000000000
0)
0*
#163000000000000000
1)
1*
#164000000000000000
0)
0*
#165000000000000000
1)
1*
#166000000000000000
0)
0*
#167000000000000000
1)
1*
#168000000000000000
0)
0*
#169000000000000000
1)
1*
#170000000000000000
1#
0)
0*
1-
#171000000000000000
1)
1*
b10 3
#172000000000000000
0)
0*
#173000000000000000
0&
1'
1)
1*
00
11
